jinja_filters.py
jinja_filters-0.1.0.dist-info/LICENSE
jinja_filters-0.1.0.dist-info/WHEEL
jinja_filters-0.1.0.dist-info/METADATA
jinja_filters-0.1.0.dist-info/RECORD
